__init__.py
main.py
metadata.py
build/__init__.py
build/cache.py
build/graph.py
helper/__init__.py
helper/artifact.py
helper/debug.py
helper/dictionary.py
helper/docker.py
helper/interface.py
helper/logging.py
rule/__init__.py
rule/load.py
rule/rules/__init__.py
rule/rules/abstract.py
rule/rules/chain.py
rule/rules/file.py
rule/rules/function.py
rule/rules/get_item.py
rule/rules/image.py
rule/rules/reference.py
rule/rules/string.py
pezel-0.0.1.dist-info/LICENSE
pezel-0.0.1.dist-info/METADATA
pezel-0.0.1.dist-info/WHEEL
pezel-0.0.1.dist-info/top_level.txt
pezel-0.0.1.dist-info/RECORD
