Metadata-Version: 2.1
Name: pezel
Version: 0.0.1
Summary: Building with Docker
Author: Brok Bucholtz
License: GNU GENERAL PUBLIC LICENSE
Project-URL: Homepage, https://github.com/Brok-Bucholtz/pezel
Project-URL: Bug Tracker, https://github.com/Brok-Bucholtz/pezel/issues
Requires-Python: >=3.9
License-File: LICENSE
